[
  {
    "id": 1,
    "ProductName": "Glass Shield, The",
    "ProductCategory": "Crime|Drama",
    "ProductTag": "Bread - White, Sliced"
  }, {
    "id": 2,
    "ProductName": "The Raid: Redemption",
    "ProductCategory": "Action|Crime",
    "ProductTag": "Soda Water - Club Soda, 355 Ml"
  }, {
    "id": 3,
    "ProductName": "Breaking the Surface",
    "ProductCategory": "Drama",
    "ProductTag": "Pop - Club Soda Can"
  }, {
    "id": 4,
    "ProductName": "Makai Tensho Samurai Reincarnation",
    "ProductCategory": "Action|Fantasy|Horror",
    "ProductTag": "Sorrel - Fresh"
  }, {
    "id": 5,
    "ProductName": "On Moonlight Bay",
    "ProductCategory": "Comedy|Musical",
    "ProductTag": "Lamb - Whole, Frozen"
  }
]
  